ms2lipid/__init__.py
ms2lipid/ms2lipid.py
ms2lipid-0.1.8.dist-info/METADATA
ms2lipid-0.1.8.dist-info/WHEEL
ms2lipid-0.1.8.dist-info/top_level.txt
ms2lipid-0.1.8.dist-info/RECORD
